[
    {
        "productId": "AEDFXA1EN018",
        "productGroup": "STOCK",
        "name": "ADES INTERNATIONAL",
        "alias": "ADES",
        "productType": "STD-Standard",
        "category": "STD-Standard",
        "currency": "USD",
        "priceId": "ADES.L",
        "priceConversionFactor": "1",
		"author": "IE65TM",
		"approvedBy": "JX88FF",
        "status": "Approved"
    },
    {
        "productId": "AN8068571086",
        "productGroup": "STOCK",
        "name": "SCHLUMBERGER LTD",
        "alias": "SLBP",
        "productType": "STD-Standard",
        "category": "STD-Standard",
        "currency": "EUR",
        "priceId": "SLBP.PA",
        "priceConversionFactor": "1",
		"author": "AM00ST",
		"approvedBy": "",
        "status": "Draft"
    },
    {
        "productId": "ANN4327C1220",
        "productGroup": "STOCK",
        "name": "HUNTER DOUGLAS",
        "alias": "HUDN",
        "productType": "STD-Standard",
        "category": "STD-Standard",
        "currency": "EUR",
        "priceId": "HUDN.AS",
        "priceConversionFactor": "1",
		"author": "AM00ST",
		"approvedBy": "IE65TM",
        "status": "Approved"
    },
    {
        "productId": "ANN4327C1303",
        "productGroup": "STOCK",
        "name": "HUNTER DOUGLAS",
        "alias": "HUDNP",
        "productType": "STD-Standard",
        "category": "STD-Standard",
        "currency": "EUR",
        "priceId": "HUDN_p.AS",
        "priceConversionFactor": "1",
		"author": "IE65TM",
		"approvedBy": "AM00ST",
        "status": "Approved"
    },
    {
        "productId": "ARP290071876",
        "productGroup": "STOCK",
        "name": "SDAD COM DEL PLATA",
        "alias": "SCDP",
        "productType": "STD-Standard",
        "category": "STD-Standard",
        "currency": "CHF",
        "priceId": "CADOn.S",
        "priceConversionFactor": "1",
		"author": "IE65TM",
		"approvedBy": "AM00ST",
        "status": "Approved"
    },
    {
        "productId": "BE0000336454",
        "productGroup": "BOND",
        "name": "BELGIUM 22 6 2038",
        "alias": "BEL50",
        "productType": "STD-Standard",
        "category": "STD-Standard",
        "currency": "EUR",
        "priceId": "BE336=RRPS",
        "priceConversionFactor": "1",
		"author": "IE65TM",
		"approvedBy": "JX88FF",
        "status": "Approved"
    },
    {
        "productId": "BE0000337460",
        "productGroup": "BOND",
        "name": "1BELGIUM26OLO1",
        "alias": "BE601",
        "productType": "STD-Standard",
        "category": "STD-Standard",
        "currency": "EUR",
        "priceId": "BE337=RRPS",
        "priceConversionFactor": "1",
		"author": "AM00ST",
		"approvedBy": "JX88FF",
        "status": "Approved"
    },
    {
        "productId": "BE0000339482",
        "productGroup": "BOND",
        "name": "BELGIUM.2 22OCT2023",
        "alias": "BE339",
        "productType": "STD-Standard",
        "category": "STD-Standard",
        "currency": "EUR",
        "priceId": "BE339=RRPS",
        "priceConversionFactor": "1",
		"author": "AM00ST",
		"approvedBy": "JX88FF",
        "status": "Approved"
    },
    {
        "productId": "BE0000340498",
        "productGroup": "BOND",
        "name": "BEGV 2.150 22-JUN-20",
        "alias": "BE498",
        "productType": "STD-Standard",
        "category": "STD-Standard",
        "currency": "EUR",
        "priceId": "BE340=RRPS",
        "priceConversionFactor": "1",
		"author": "IE65TM",
		"approvedBy": "",
        "status": "Draft"
    },
    {
        "productId": "06828709H9",
        "productGroup": "RIGHT",
        "name": "SACYR-RHTS011220",
        "alias": "ES9HR",
        "productType": "STD-Standard",
        "category": "STD-Standard",
        "currency": "EUR",
        "priceId": "SCYR_r.MC",
        "priceConversionFactor": "1",
		"author": "IE65TM",
		"approvedBy": "",
        "status": "Cancelled"
    },
    {
        "productId": "FR0014000IK6",
        "productGroup": "RIGHT",
        "name": "DRONE VOLT DS",
        "alias": "FRIDS",
        "productType": "STD-Standard",
        "category": "STD-Standard",
        "currency": "EUR",
        "priceId": "ALDRV_r.PA",
        "priceConversionFactor": "1",
		"author": "IE65TM",
		"approvedBy": "JX88FF",
        "status": "Approved"
    },
    {
        "productId": "FR0014000IN0",
        "productGroup": "RIGHT",
        "name": "ALSTOM DS",
        "alias": "ALST",
        "productType": "STD-Standard",
        "category": "STD-Standard",
        "currency": "EUR",
        "priceId": "ALSO_r.PA",
        "priceConversionFactor": "1",
		"author": "IE65TM",
		"approvedBy": "JX88FF",
        "status": "Approved"
    },
    {
        "productId": "GB00BJP49W43",
        "productGroup": "RIGHT",
        "name": "ROLLS-ROYCE HOLDINGS",
        "alias": "G9W43",
        "productType": "STD-Standard",
        "category": "STD-Standard",
        "currency": "GBP",
        "priceId": "RRn.L",
        "priceConversionFactor": "0.01",
		"author": "IE65TM",
		"approvedBy": "JX88FF",
        "status": "Approved"
    },
    {
        "productId": "GDR1RI",
        "productGroup": "RIGHT",
        "name": "GDR1RI",
        "alias": "GDR1R",
        "productType": "STD-Standard",
        "category": "STD-Standard",
        "currency": "USD",
        "priceId": "",
        "priceConversionFactor": "",
		"author": "IE65TM",
		"approvedBy": "",
        "status": "Draft"
    }
]